zhangtest3/__init__.py
zhangtest3/demo1.py
zhangtest3-0.0.0.dist-info/LICENSE
zhangtest3-0.0.0.dist-info/METADATA
zhangtest3-0.0.0.dist-info/WHEEL
zhangtest3-0.0.0.dist-info/top_level.txt
zhangtest3-0.0.0.dist-info/RECORD
