Metadata-Version: 2.1
Name: zhangtest3
Version: 0.0.0
Summary: 第一次发布，测试一下
Author: zhanglie
Author-email: 3277706060@qq.com
License: UNKNOWN
Platform: UNKNOWN
License-File: LICENSE
